diy/__init__.py
diy/container.py
diy/debug.py
diy/errors.py
diy/specification.py
diy/validation.py
diy-0.1.0.dist-info/METADATA
diy-0.1.0.dist-info/WHEEL
diy-0.1.0.dist-info/RECORD
