Metadata-Version: 2.3
Name: diy
Version: 0.1.0
Summary: Add your description here
Author-email: Niclas van Eyk <niclas.eyk@gmail.com>
Requires-Python: >=3.12
